geolime/__init__.py
geolime-1.4.0.dist-info/licenses/LICENSE
geolime-1.4.0.dist-info/METADATA
geolime-1.4.0.dist-info/WHEEL
geolime-1.4.0.dist-info/top_level.txt
geolime-1.4.0.dist-info/RECORD
