Metadata-Version: 2.4
Name: geolime
Version: 1.4.0
Summary: GeoLime Geostats Library
Author-email: DeepLime <contact@deeplime.io>
Project-URL: Homepage, https://github.com/deeplime-io/geolime-pypi-package
Project-URL: Repository, https://github.com/deeplime-io/geolime-pypi-package
Keywords: geolime,geostats
Classifier: Programming Language :: Python :: 3
Classifier: Operating System :: OS Independent
Requires-Python: >=3.8
License-File: LICENSE
Dynamic: license-file
